MANIFEST.in
README.rst
setup.py
pptshape/__init__.py
pptshape/directive.py
pptshape/ppt.py
pptshape.egg-info/PKG-INFO
pptshape.egg-info/SOURCES.txt
pptshape.egg-info/dependency_links.txt
pptshape.egg-info/requires.txt
pptshape.egg-info/top_level.txt
test/test_ppt.py