Metadata-Version: 1.1
Name: pptshape
Version: 0.0.3
Summary: Extract images from PowerPoint presentation files for Sphinx.
Home-page: https://github.com/atsuoishimoto/pptshape
Author: Atsuo Ishimoto
Author-email: ishimoto@gembook.org
License: BSD
Platform: UNKNOWN
Classifier: Development Status :: 5 - Production/Stable
Classifier: Topic :: Software Development :: Documentation
Classifier: License :: OSI Approved :: BSD License
Classifier: Programming Language :: Python :: 2.7
Classifier: Programming Language :: Python :: 3
